{
  "rituals": [
    {
      "id": "rahu-jaap ",
      "featured": true,
      "featuredRank": 12,
      "featuredNote": {
        "en": "rahu jaap .",
        "hi": "राहु जाप"
      },

      "tags": ["temple", "shiv", "jyotirlinga"],
      "images": [
        "assets/images/rituals/0.jpeg",
        "assets/images/rituals/1.jpeg",
        "assets/images/rituals/2.jpeg",
        "assets/images/rituals/3.jpeg",
        "assets/images/rituals/4.jpeg",
        "assets/images/rituals/5.jpeg"
      ],

      "title": {
        "hi": "राहु वैदिक ज्योतिष में नवग्रहों में से एक छाया ग्रह माना जाता है। यह भौतिक ग्रह नहीं है, बल्कि चंद्रमा और सूर्य के मार्ग के छेदन बिंदु (लूनर नोड) का प्रतीक है। जन्मकुंडली में राहु की स्थिति व्यक्ति के जीवन में भ्रम, अचानक घटनाएँ, विदेश योग, राजनीति, तकनीक, नशा, मायाजाल आदि का संकेत देती है।* राहु जाप करने के मुख्य कारण1️ कुंडली में राहु दोष शांति हेतुयदि राहु अशुभ भाव में हो, नीच का हो, या पाप ग्रहों से पीड़ित हो तो:मानसिक तनावनिर्णय में भ्रमझूठे आरोपअचानक हानिनशे या बुरी संगति की प्रवृत्तिऐसी स्थिति में राहु जाप शांति देता है।2️ राहु महादशा / अंतरदशा मेंजब राहु की दशा चलती है, तो जीवन में उतार-चढ़ाव बढ़ सकते हैं। जाप से:बाधाएँ कम होती हैंमानसिक संतुलन मिलता हैअचानक संकट टलते हैं3️ कालसर्प दोष मेंकई ज्योतिषाचार्य मानते हैं कि कालसर्प योग में राहु-केतु की विशेष शांति आवश्यक होती है।4️ सफलता और विदेश योग के लिएराहु आधुनिक तकनीक, राजनीति, मीडिया, विदेशी व्यापार और रहस्यमयी विद्या का कारक है। शुभ राहु उन्नति देता है। .",
        "en": "Rahu Chanting Rahu is considered a shadow planet in Vedic astrology. It is not a physical planet, but symbolizes the lunar node (intersection point) of the paths of the Moon and the Sun. The position of Rahu in the horoscope indicates confusion, sudden events, foreign influences, politics, technology, addiction, and illusions in a person's life. * Main reasons for chanting Rahu: 1? To pacify Rahu Dosha in a horoscope, if Rahu is in an inauspicious house, is in a low position, or is afflicted by malefic planets: Mental stress Confusion in judgment False accusations Sudden loss Addiction to addiction or bad company In such situations, Rahu chanting brings peace. 2? During Rahu Mahadasha/Antardasha, when Rahu's period is in effect, ups and downs in life can increase. Chanting: reduces obstacles, provides mental balance, and averts sudden crises. 3? In Kaalsarp Dosha, many astrologers believe that special pacification of Rahu and Ketu is necessary in Kaalsarp Yoga. 4? Success and For foreign yoga, Rahu is the significator of modern technology, politics, media, foreign trade, and occult knowledge. Auspicious Rahu brings progress."
      }
    }
  ]
}
